pyono/__init__.py
pyono/api.py
pyono/softsim/__init__.py
pyono/softsim/crypto.py
pyono/softsim/profile.py
pyono-0.0.1.dist-info/METADATA
pyono-0.0.1.dist-info/WHEEL
pyono-0.0.1.dist-info/RECORD
