Metadata-Version: 2.4
Name: pyono
Version: 0.0.1
Summary: Onomondo SoftSIM API managing libraries
Project-URL: Homepage, https://github.com/ltsistb/onomondo-pyono
Project-URL: Repository, https://github.com/ltsistb/onomondo-pyono.git
Author-email: ltsistb <ltsistb@proton.me>
Maintainer-email: ltsistb <ltsistb@proton.me>
License-Expression: GPL-3.0-or-later
Keywords: onomondo,softsim
Classifier: Development Status :: 4 - Beta
Classifier: Operating System :: OS Independent
Classifier: Programming Language :: Python
Requires-Python: >=3.11
Requires-Dist: pycryptodome
Requires-Dist: requests
